[
  {
    "employer_name": "IBM",
    "job_title": "Technical Support Engineer",
    "job_city": "POUGHKEEPSIE",
    "job_state": "US",
    "job_posted_at": "1d",
    "job_description": "data science job for the role Technical Support Engineer",
    "job_apply_link": "https://ibmglobal.avature.net/en_US/careers/JobDetail?jobId=63081&source=WEB_Search_NA",
    "id": "ibm-technical-support-engineer-poughkeepsie"
  },
  {
    "employer_name": "Google",
    "job_title": "Software Engineer III, AI/ML, Road Data Quality",
    "job_city": "Mountain View",
    "job_state": "CA",
    "job_posted_at": "1h",
    "job_description": "data science job for the role Software Engineer III, AI/ML, Road Data Quality",
    "job_apply_link": "https://www.google.com/about/careers/applications/jobs/results//jobs/results/111640826353722054-software-engineer-iii-aiml-road-data-quality?location=United%20States&target_level=EARLY&target_level=MID&target_level=INTERN_AND_APPRENTICE&q=data%20science&page=3",
    "id": "google-software-engineer-iii-ai-ml-road-data-quality-mountain-view"
  }
]